[{"id":1,"humanresource":{"id":1,"humanresourcename":"Agent accueil_1"},"humanresourcecategory":{"id":19,"categoryname":"Agent accueil","__initializer__":null,"__cloner__":null,"__isInitialized__":true}},{"id":2,"humanresource":{"id":2,"humanresourcename":"Agent accueil_2"},"humanresourcecategory":{"id":19,"categoryname":"Agent accueil","__initializer__":null,"__cloner__":null,"__isInitialized__":true}},{"id":3,"humanresource":{"id":3,"humanresourcename":"Infirmier (IDE)_3"},"humanresourcecategory":{"id":12,"categoryname":"Infirmier (IDE)","__initializer__":null,"__cloner__":null,"__isInitialized__":true}},{"id":4,"humanresource":{"id":4,"humanresourcename":"Infirmier (IDE)_4"},"humanresourcecategory":{"id":12,"categoryname":"Infirmier (IDE)","__initializer__":null,"__cloner__":null,"__isInitialized__":true}},{"id":5,"humanresource":{"id":5,"humanresourcename":"Infirmier (IDE)_5"},"humanresourcecategory":{"id":12,"categoryname":"Infirmier (IDE)","__initializer__":null,"__cloner__":null,"__isInitialized__":true}},{"id":6,"humanresource":{"id":6,"humanresourcename":"Psychologue_6"},"humanresourcecategory":{"id":20,"categoryname":"Psychologue","__initializer__":null,"__cloner__":null,"__isInitialized__":true}},{"id":7,"humanresource":{"id":7,"humanresourcename":"Psychologue_7"},"humanresourcecategory":{"id":20,"categoryname":"Psychologue","__initializer__":null,"__cloner__":null,"__isInitialized__":true}},{"id":11,"humanresource":{"id":10,"humanresourcename":"Neuropsy_10"},"humanresourcecategory":{"id":15,"categoryname":"Neurologue","__initializer__":null,"__cloner__":null,"__isInitialized__":true}},{"id":12,"humanresource":{"id":10,"humanresourcename":"Neuropsy_10"},"humanresourcecategory":{"id":21,"categoryname":"Neuropsy","__initializer__":null,"__cloner__":null,"__isInitialized__":true}},{"id":13,"humanresource":{"id":8,"humanresourcename":"Neuropsy_8"},"humanresourcecategory":{"id":15,"categoryname":"Neurologue","__initializer__":null,"__cloner__":null,"__isInitialized__":true}},{"id":14,"humanresource":{"id":8,"humanresourcename":"Neuropsy_8"},"humanresourcecategory":{"id":21,"categoryname":"Neuropsy","__initializer__":null,"__cloner__":null,"__isInitialized__":true}},{"id":15,"humanresource":{"id":9,"humanresourcename":"Neuropsy_9"},"humanresourcecategory":{"id":15,"categoryname":"Neurologue","__initializer__":null,"__cloner__":null,"__isInitialized__":true}},{"id":16,"humanresource":{"id":9,"humanresourcename":"Neuropsy_9"},"humanresourcecategory":{"id":21,"categoryname":"Neuropsy","__initializer__":null,"__cloner__":null,"__isInitialized__":true}},{"id":17,"humanresource":{"id":11,"humanresourcename":"Neurologue_11"},"humanresourcecategory":{"id":15,"categoryname":"Neurologue","__initializer__":null,"__cloner__":null,"__isInitialized__":true}}]