[{"id":1,"materialresource":{"id":1,"materialresourcename":"Box Pr\u00e9levement_1"},"materialresourcecategory":{"id":16,"categoryname":"Box Pr\u00e9levement","__initializer__":null,"__cloner__":null,"__isInitialized__":true}},{"id":2,"materialresource":{"id":2,"materialresourcename":"Box Pr\u00e9levement_2"},"materialresourcecategory":{"id":16,"categoryname":"Box Pr\u00e9levement","__initializer__":null,"__cloner__":null,"__isInitialized__":true}},{"id":3,"materialresource":{"id":3,"materialresourcename":"Salle consultation_3"},"materialresourcecategory":{"id":11,"categoryname":"Salle consultation","__initializer__":null,"__cloner__":null,"__isInitialized__":true}},{"id":4,"materialresource":{"id":4,"materialresourcename":"Salle consultation_4"},"materialresourcecategory":{"id":11,"categoryname":"Salle consultation","__initializer__":null,"__cloner__":null,"__isInitialized__":true}}]